{
    "capabilities-landing": {
        "breadcrumbs": {
            "breadcrumbOptions": [
                {
                    "titleLabel": "Capabilities"
                }
            ]
        }
    },
    "contact-us": {
        "breadcrumbs": {
            "breadcrumbOptions": [
                {
                    "titleLabel": "Contact Us"
                }
            ]
        }
    },
    "staff-application": {
        "breadcrumbs": {
            "breadcrumbOptions": [
                {
                    "titleLabel": "Careers",
                    "url": "/careers-landing.html"
                },
                {
                    "titleLabel": "Professional Staff",
                    "url": "/careers-detail.html"
                },
                {
                    "titleLabel": "Opportunities",
                    "url": "/careers-detail.html"
                },
                {
                    "titleLabel": "Client Accounting Applications Development Supervisor",
                    "url": "/careers-detail.html"
                },
                {
                    "titleLabel": "Apply"
                }
            ]
        }
    },
    "site-search": {
        "breadcrumbs": {
            "breadcrumbOptions": [
                {
                    "titleLabel": "Site Search"
                }
            ]
        }
    }
}
